{
  "engaged": {
    "definition": "Involved and paying attention; actively participating.",
    "chinese": "投入的",
    "example": "An engaged parent watches and listens carefully."
  },
  "observation": {
    "definition": "The act of watching something carefully.",
    "chinese": "觀察",
    "example": "Careful observation helps you understand your child."
  },
  "opportunity": {
    "definition": "A chance to do something.",
    "chinese": "機會",
    "example": "She waited for an opportunity to speak."
  },
  "compose": {
    "definition": "To put together; to prepare something carefully.",
    "chinese": "構思；撰寫",
    "example": "Instead of composing a reply, just listen."
  },
  "response": {
    "definition": "An answer or reaction to something.",
    "chinese": "回應",
    "example": "Her response was kind and thoughtful."
  },
  "reply": {
    "definition": "An answer given back to someone.",
    "chinese": "回答",
    "example": "He thought about his reply before speaking."
  },
  "scary": {
    "definition": "Making you feel afraid.",
    "chinese": "可怕的",
    "example": "Letting someone affect you can feel scary."
  },
  "unspoken": {
    "definition": "Not said out loud; understood without words.",
    "chinese": "未說出口的",
    "example": "There was an unspoken fear between them."
  },
  "disappear": {
    "definition": "To stop existing or being seen.",
    "chinese": "消失",
    "example": "If you listen to others, you won't disappear."
  },
  "drained": {
    "definition": "Feeling very tired and without energy.",
    "chinese": "精疲力竭的",
    "example": "She felt drained after caring for the baby all day."
  },
  "neediness": {
    "definition": "The state of needing a lot of attention or care.",
    "chinese": "需求感強；依賴",
    "example": "A baby's neediness can feel overwhelming."
  },
  "struggle": {
    "definition": "A great effort to do something difficult.",
    "chinese": "掙扎",
    "example": "It was a struggle to stay patient."
  },
  "demands": {
    "definition": "Strong requests that are hard to refuse.",
    "chinese": "要求",
    "example": "The baby's demands felt never-ending."
  },
  "defend": {
    "definition": "To protect yourself from something.",
    "chinese": "防禦",
    "example": "She tried to defend herself against feeling overwhelmed."
  },
  "knack": {
    "definition": "A natural skill or ability to do something well.",
    "chinese": "訣竅；本領",
    "example": "She got the knack of reading the baby's signals."
  },
  "pre-empting": {
    "definition": "Doing something before it happens to prevent a problem.",
    "chinese": "預先阻止；搶先",
    "example": "She learned to pre-empt the baby's crying."
  },
  "distressed": {
    "definition": "Very upset and worried.",
    "chinese": "痛苦的；焦慮的",
    "example": "The baby became distressed when left alone."
  },
  "commentary": {
    "definition": "A description of what is happening as it happens.",
    "chinese": "解說；旁白",
    "example": "She gave a running commentary as she did housework."
  },
  "housework": {
    "definition": "Work done to keep a house clean and tidy.",
    "chinese": "家務",
    "example": "She talked to the baby while doing housework."
  },
  "tasks": {
    "definition": "Jobs or pieces of work that need to be done.",
    "chinese": "任務",
    "example": "Daily tasks can be shared with your child."
  },
  "chat": {
    "definition": "To talk in a friendly, informal way.",
    "chinese": "聊天",
    "example": "The baby would chat back with sounds."
  },
  "thrill": {
    "definition": "A sudden feeling of excitement.",
    "chinese": "興奮；快感",
    "example": "It's not that she got a thrill from looking at leaves."
  },
  "examining": {
    "definition": "Looking at something very carefully.",
    "chinese": "仔細查看",
    "example": "She found peace in examining small things with her child."
  },
  "leaf": {
    "definition": "The flat green part of a plant or tree.",
    "chinese": "葉子",
    "example": "The baby loved looking at every leaf."
  },
  "ladybird": {
    "definition": "A small round insect that is usually red with black spots.",
    "chinese": "瓢蟲",
    "example": "They watched a ladybird crawl across a leaf."
  },
  "concentrate": {
    "definition": "To focus your attention on something.",
    "chinese": "專注",
    "example": "She watched her baby concentrate on a toy."
  },
  "awe": {
    "definition": "A feeling of great respect and wonder.",
    "chinese": "敬畏",
    "example": "Watching her child filled her with awe."
  },
  "responsive": {
    "definition": "Reacting quickly and positively.",
    "chinese": "有回應的",
    "example": "The child was less responsive when talked at."
  },
  "mellowed": {
    "definition": "Became more gentle and relaxed over time.",
    "chinese": "變得溫和",
    "example": "Parenting has mellowed her personality."
  },
  "expanded": {
    "definition": "Made bigger or wider; grew.",
    "chinese": "擴展了",
    "example": "She felt expanded by her child's influence."
  },
  "incapable": {
    "definition": "Not able to do something.",
    "chinese": "無能力的",
    "example": "She felt incapable of deep love before becoming a parent."
  },
  "impart": {
    "definition": "To share knowledge or information with someone.",
    "chinese": "傳達；給予",
    "example": "She learned to listen instead of just imparting her ideas."
  },
  "pattern": {
    "definition": "A regular way of doing or behaving.",
    "chinese": "模式",
    "example": "She learned a new pattern of listening."
  },
  "formed": {
    "definition": "Created or developed.",
    "chinese": "形成的",
    "example": "They formed a deep and loving relationship."
  }
}
