{
  "weaning": {
    "definition": "Gradually changing a baby from drinking only milk to eating solid food.",
    "chinese": "斷奶",
    "example": "She was weaning her daughter from breast milk to solid food."
  },
  "vegetables": {
    "definition": "Plants that are eaten as food, like carrots and broccoli.",
    "chinese": "蔬菜",
    "example": "The child ate her vegetables while being sung to."
  },
  "spaghetti": {
    "definition": "Long, thin pieces of pasta.",
    "chinese": "義大利麵",
    "example": "The child ate spaghetti sitting on her rug."
  },
  "rug": {
    "definition": "A soft piece of thick cloth that covers part of a floor.",
    "chinese": "地毯",
    "example": "The child sat on her special rug in the middle of the room."
  },
  "fantasize": {
    "definition": "To imagine something you wish would happen, but probably will not.",
    "chinese": "幻想",
    "example": "Parents sometimes fantasize about future problems that never happen."
  },
  "pacifier": {
    "definition": "A rubber object that a baby sucks on to feel calm.",
    "chinese": "安撫奶嘴",
    "example": "She worried her child would never give up her pacifier."
  },
  "accompany": {
    "definition": "To go somewhere together with someone.",
    "chinese": "陪伴",
    "example": "Will Mr Squidgy have to accompany him to work?"
  },
  "phase": {
    "definition": "A temporary period or stage that someone goes through.",
    "chinese": "階段",
    "example": "Almost everything with children is a phase."
  },
  "odd": {
    "definition": "Strange or unusual.",
    "chinese": "奇怪的",
    "example": "Go with what works, however odd it seems."
  },
  "implement": {
    "definition": "To start using a new plan or system.",
    "chinese": "實施",
    "example": "If what works stops working, implement a change."
  },
  "modelling": {
    "definition": "Showing someone how to behave by doing it yourself.",
    "chinese": "示範",
    "example": "Modelling flexibility makes change easier for everyone."
  },
  "flexibility": {
    "definition": "The ability to change or adapt easily.",
    "chinese": "靈活性",
    "example": "Flexibility is an important skill for both parents and children."
  },
  "snoring": {
    "definition": "Making loud breathing sounds while sleeping.",
    "chinese": "打呼",
    "example": "Eventually your children will get fed up with your snoring."
  },
  "pile": {
    "definition": "To put a lot of things on top of each other.",
    "chinese": "堆疊",
    "example": "They piled the whole family into two double beds pushed together."
  },
  "lunchtimes": {
    "definition": "The times during the day when people eat lunch.",
    "chinese": "午餐時間",
    "example": "She worried about her daughter's behaviour at school lunchtimes."
  },
  "refuse": {
    "definition": "To say no to something; to not accept.",
    "chinese": "拒絕",
    "example": "What if she always refuses to eat at a table?"
  },
  "date": {
    "definition": "A planned meeting with someone you are interested in romantically.",
    "chinese": "約會",
    "example": "She even worried about her daughter's first date."
  },
  "restaurants": {
    "definition": "Places where you pay to eat meals prepared by others.",
    "chinese": "餐廳",
    "example": "She worried her child would not behave in restaurants."
  }
}
